dagster_blueprints/__init__.py
dagster_blueprints/blueprint.py
dagster_blueprints/blueprint_assets_definition.py
dagster_blueprints/cli.py
dagster_blueprints/databricks_blueprint.py
dagster_blueprints/load_from_yaml.py
dagster_blueprints/shell_command_blueprint.py
dagster_blueprints/version.py
dagster_blueprints-1.9.11.dist-info/LICENSE
dagster_blueprints-1.9.11.dist-info/METADATA
dagster_blueprints-1.9.11.dist-info/WHEEL
dagster_blueprints-1.9.11.dist-info/entry_points.txt
dagster_blueprints-1.9.11.dist-info/top_level.txt
dagster_blueprints-1.9.11.dist-info/RECORD
